eegpp2/TOKEN.txt
eegpp2/__init__.py
eegpp2/__main__.py
eegpp2/dataloader.py
eegpp2/dataset.py
eegpp2/inference.py
eegpp2/logger.py
eegpp2/overwrite_template.py
eegpp2/params.py
eegpp2/trainer.py
eegpp2/trainer_backup.py
eegpp2/visualization.py
eegpp2/configs/__init__.py
eegpp2/configs/cnn1d_config.yml
eegpp2/configs/fft2cwout_config.yml
eegpp2/configs/fftcnn1dnc_config.yml
eegpp2/configs/ffttransnc_config.yml
eegpp2/configs/stftcnn1dnc_config.yml
eegpp2/configs/stfttransnc_config.yml
eegpp2/configs/transformer_config.yml
eegpp2/configs/wtcnn1dnc_config.yml
eegpp2/configs/wtresnet501dnc_config.yml
eegpp2/data/__init__.py
eegpp2/models/__init__.py
eegpp2/models/cnn1d2c.py
eegpp2/models/fft2c.py
eegpp2/models/fftcnn1dnc.py
eegpp2/models/ffttransnc.py
eegpp2/models/stft2c.py
eegpp2/models/stftcnn1dnc.py
eegpp2/models/stfttransnc.py
eegpp2/models/wtcnn1dnc.py
eegpp2/models/wtresnet1dnc.py
eegpp2/models/baseline/__init__.py
eegpp2/models/baseline/cnn1d.py
eegpp2/models/baseline/fft.py
eegpp2/models/baseline/resnet.py
eegpp2/models/baseline/transformer.py
eegpp2/out/__init__.py
eegpp2/utils/__init__.py
eegpp2/utils/common_utils.py
eegpp2/utils/config_utils.py
eegpp2/utils/data_utils.py
eegpp2/utils/model_utils.py
eegpp2_beta-0.1.7.dist-info/licenses/LICENSE
eegpp2_beta-0.1.7.dist-info/METADATA
eegpp2_beta-0.1.7.dist-info/WHEEL
eegpp2_beta-0.1.7.dist-info/top_level.txt
eegpp2_beta-0.1.7.dist-info/RECORD
